baseai/__init__.py
baseai/agent.py
baseai/baseai_client.py
baseai/models.py
baseai/thread.py
baseai/tools.py
baseai/api/__init__.py
baseai/api/agents.py
baseai/api/threads.py
baseai/api/utils.py
baseai_sdk-1.0.1.dist-info/METADATA
baseai_sdk-1.0.1.dist-info/WHEEL
baseai_sdk-1.0.1.dist-info/top_level.txt
baseai_sdk-1.0.1.dist-info/RECORD
